liveramp_automation/helper_bucket.py
liveramp_automation/helper_file.py
liveramp_automation/helper_login.py
liveramp_automation/helper_notification.py
liveramp_automation/util_allure.py
liveramp_automation/util_log.py
liveramp_automation/util_parsers.py
liveramp_automation/util_playwright.py
liveramp_automation/util_request.py
liveramp_automation/util_selenium.py
liveramp_automation/util_time.py
my_automation_framework-0.1.9.2.dist-info/METADATA
my_automation_framework-0.1.9.2.dist-info/WHEEL
my_automation_framework-0.1.9.2.dist-info/top_level.txt
my_automation_framework-0.1.9.2.dist-info/RECORD
