Metadata-Version: 2.1
Name: my-automation-framework
Version: 0.1.9.2
Summary: This is the base liveramp_automation_framework
Home-page: https://github.com/LiveRamp/qe_api_framework
Author: Jasmine Qian
Author-email: jasmine.qian@liveramp.com
Requires-Dist: pytest
Requires-Dist: pytest-bdd
Requires-Dist: pytest-playwright
Requires-Dist: allure-pytest-bdd
Requires-Dist: allure-python-commons
Requires-Dist: google
Requires-Dist: google-api-core
Requires-Dist: google-auth
Requires-Dist: google-cloud-bigquery
Requires-Dist: google-cloud-core
Requires-Dist: google-cloud-storage
Requires-Dist: google-crc32c
Requires-Dist: google-resumable-media
Requires-Dist: googleapis-common-protos
Requires-Dist: PyYAML
Requires-Dist: pytest-json-report
Requires-Dist: pytest-json
Requires-Dist: pytest-xdist
Requires-Dist: requests
Requires-Dist: selenium (==4.8.3)
Requires-Dist: pytest-bdd (==6.1.1)
Requires-Dist: PyYAML (==6.0)
Requires-Dist: webdriver-manager (==3.8.6)
Requires-Dist: retrying (==1.3.4)
